exptree/__init__.py
exptree/src/__init__.py
exptree/src/exp_view.py
exptree/src/run_view.py
exptree/src/tests.py
exptree/src/tree.py
exptree/src/tree_manager.py
exptree-0.1.0.dist-info/LICENSE
exptree-0.1.0.dist-info/METADATA
exptree-0.1.0.dist-info/WHEEL
exptree-0.1.0.dist-info/RECORD
