Metadata-Version: 2.3
Name: exptree
Version: 0.1.0
Summary: Track your ML experiments, data and other artifacts with minimal overhead and configs. A light, easy Experiment tracking framework
License: Apache-2.0 license
Author: Nishanth
Author-email: nishanthkc009@gmail.com
Requires-Python: >=3.9
Classifier: License :: Other/Proprietary License
Classifier: Programming Language :: Python :: 3
Classifier: Programming Language :: Python :: 3.9
Classifier: Programming Language :: Python :: 3.10
Classifier: Programming Language :: Python :: 3.11
Classifier: Programming Language :: Python :: 3.12
Classifier: Programming Language :: Python :: 3.13
Requires-Dist: ipywidgets (>=8.1.5,<9.0.0)
Requires-Dist: jupyter (>=1.1.1,<2.0.0)
Requires-Dist: networkx (==3.2)
Requires-Dist: notebook (>=7.3.3,<8.0.0)
Requires-Dist: pandas (>=2.2.3,<3.0.0)
Requires-Dist: pytest (>=8.3.5,<9.0.0)
Requires-Dist: scikit-learn (>=1.6.1,<2.0.0)
